easyfut/__init__.py
easyfut/main.py
easyfut/server.py
easyfut/conf/__init__.py
easyfut/conf/easyfut-template.conf
easyfut/web/__init__.py
easyfut/web/response.py
easyfut/web/routes.py
easyfut/web/handlers/__init__.py
easyfut/web/handlers/account.py
easyfut/web/handlers/base.py
easyfut/web/handlers/klines.py
easyfut/web/handlers/order.py
easyfut/web/handlers/position.py
easyfut/web/handlers/quote.py
easyfut/web/handlers/ticks.py
easyfut-1.0.4.dist-info/LICENSE
easyfut-1.0.4.dist-info/METADATA
easyfut-1.0.4.dist-info/WHEEL
easyfut-1.0.4.dist-info/entry_points.txt
easyfut-1.0.4.dist-info/top_level.txt
easyfut-1.0.4.dist-info/RECORD
