Metadata-Version: 2.1
Name: easyfut
Version: 1.0.4
Summary: 简单期货行情&交易HTTP接口API，基于TqSdk
Home-page: https://github.com/hanwanhe/easyfut-python
Author: hanwanhe
Author-email: hanwanhe@foxmail.com
License: UNKNOWN
Platform: UNKNOWN
Classifier: Programming Language :: Python :: 3
Classifier: License :: OSI Approved :: MIT License
Classifier: Operating System :: OS Independent
Requires-Python: >=3.6.4
Requires-Dist: tornado
Requires-Dist: tqsdk
